Workbook

Sheet Expenses
A1: Receipt ID | B1: Date | C1: Time | D1: Vendor | E1: Location | F1: Category | G1: Amount | H1: 15% Markup | I1: Billable Total | J1: Payment | K1: Receipt PDF | L1: Description
A2: R0001 | B2: 2026-07-22 | C2: 14:09 | D2: Alaska Airlines | E2: SBA-SEA / SEA-SBA | F2: Airfare | G2: 896.8 | H2: =ROUND(G2*15%,2) -> 134.52 | I2: =G2+H2 -> 1031.32 | J2: Credit card ending 3514 | K2: receipt-pdfs/R006_Alaska_Airlines_896-80.pdf | L2: Round-trip airfare for David Salter; confirmation INBEDI; e-ticket 0272152879104; Alaska 2143 SBA-SEA and Alaska 400 SEA-SBA
A3: R0002 | B3: 2026-07-23 | C3: 09:42 | D3: SBA Airport Restaurant and Coffee Shop | E3: Goleta, CA / Santa Barbara Airport | F3: Meal - outbound breakfast | G3: 18.72 | H3: =ROUND(G3*15%,2) -> 2.81 | I3: =G3+H3 -> 21.53 | J3: Mastercard ending 8609 | K3: receipt-pdfs/R001_SBA_Airport_Restaurant_and_Coffee_Shop_18-72.pdf | L3: 16 oz dirty chai, butter croissant, tax, tip; check/order #221
A4: R0003 | B4: 2026-07-23 | C4: 14:33 | D4: Hudson | E4: SEA-TAC International Airport, Seattle, WA | F4: Meal - outbound lunch | G4: 23.23 | H4: =ROUND(G4*15%,2) -> 3.48 | I4: =G4+H4 -> 26.71 | J4: Mastercard ending 8609 | K4: receipt-pdfs/R002_Hudson_23-23.pdf | L4: ET FRUMAGE, Kit Kat bar, Barq's root beer, taxes; store 2366 transaction 116010
A5: R0004 | B5: 2026-07-23 | C5: 19:00 | D5: Holiday Inn & Suites Bellingham by IHG | E5: 4260 Mitchell Way, Bellingham, WA | F5: Lodging | G5: 209.3 | H5: =ROUND(G5*15%,2) -> 31.4 | I5: =G5+H5 -> 240.7 | J5: Paid with Booking.com | K5: receipt-pdfs/R007_Holiday_Inn___Suites_Bellingham_by_IHG_209-30.pdf | L5: One night, Standard King Room, Booking.com confirmation 5674580542; total paid includes travel protection
A6: R0004a | B6: 2026-07-23 | C6: 19:00 | D6: Holiday Inn & Suites Bellingham by IHG | E6: 4260 Mitchell Way, Bellingham, WA | F6: Meal - Dinner | G6: 25 | H6: =ROUND(G6*15%,2) -> 3.75 | I6: =G6+H6 -> 28.75
A7: R0005 | B7: 2026-07-23 | C7: 14:30 | D7: Payless / Avis Budget | E7: Seattle-Tacoma International Airport | F7: Car rental | G7: 307.77 | H7: =ROUND(G7*15%,2) -> 46.17 | I7: =G7+H7 -> 353.94 | J7: Not specified in receipt | K7: receipt-pdfs/R008_Payless___Avis_Budget_307-77.pdf | L7: Mazda CX-50 or similar; confirmation 21886108US6; pickup 2026-07-23 14:30, drop-off 2026-07-24 14:30; estimated total shown on document
A8: R0006 | B8: 2026-07-24 | C8: 06:36 | D8: GURANAND | E8: 4603 S 188th St, SeaTac, WA | F8: Fuel | G8: 45.42 | H8: =ROUND(G8*15%,2) -> 6.81 | I8: =G8+H8 -> 52.23 | J8: Mastercard ending 8609 | K8: receipt-pdfs/R003_GURANAND_45-42.pdf | L8: Regular gasoline, 7.327 gallons at $6.199/gallon; pump 2 invoice 063019
A9: R0007 | B9: 2026-07-24 | C9: 07:40 | D9: Capitol Hill Foo | E9: SEATAC Airport | F9: Meal - return breakfast | G9: 15.24 | H9: =ROUND(G9*15%,2) -> 2.29 | I9: =G9+H9 -> 17.53 | J9: Mastercard ending 8609 | K9: receipt-pdfs/R004_Capitol_Hill_Foo_15-24.pdf | L9: Large latte with vanilla and blueberry muffin; check 839
A10: R0008 | B10: 2026-07-24 | C10: 13:58 | D10: Santa Barbara Airport | E10: Santa Barbara Airport | F10: Parking | G10: 46 | H10: =ROUND(G10*15%,2) -> 6.9 | I10: =G10+H10 -> 52.9 | J10: Mastercard ending 1676 | K10: receipt-pdfs/R005_Santa_Barbara_Airport_46-00.pdf | L10: Airport parking; ticket 30472590; entry 2026-07-23 09:16 AM

Sheet Itinerary
A1: Itinerary and Charges
D2: Hourly Charges | G2: Expenses | M2: Total Charges | N2: Reference
A3: Time | B3: Event | C3: Personel | D3: Hrs | E3: Rate | F3: Total | G3: Item | H3: Unit | I3: Rate | J3: Charge | K3: Markup | L3: Total
A4: 2026-07-23 08:30 PT | B4: Departed Office Drive to airport. | C4: Principal | D4: 0.5 | E4: =375/2 -> 187.5 | F4: =E4*D4 -> 93.75 | G4: 30 | H4: miles | I4: 0.7 | J4: =I4*G4 -> 21 | K4: 0 | L4: =J4*(1+K4) -> 21 | M4: =L4+F4 -> 114.75
A5: 2026-07-23 09:42 PT | B5: Outbound airport breakfast at SBA Airport Restaurant and Coffee Shop. | C5: Principal | D5: 5 | E5: =E4 -> 187.5 | F5: =E5*D5 -> 937.5 | J5: =Expenses!G3 -> 18.72 | K5: 0.15 | L5: =J5*(1+K5) -> 21.528 | M5: =L5+F5 -> 959.028 | N5: R0002
A6: 2026-07-23 10:51 PT | B6: Alaska 2143 departed Santa Barbara (SBA) for Seattle (SEA). | C6: Principal | J6: =Expenses!G2 -> 896.8 | K6: 0.15 | L6: =J6*(1+K6) -> 1031.32 | M6: =L6+F6 -> 1031.32 | N6: R0001
A7: 2026-07-23 13:26 PT | B7: Alaska 2143 arrived Seattle (SEA). | C7: Principal
A8: 2026-07-23 14:33 PT | B8: Lunch at Hudson in SEA-TAC during outbound travel. | C8: Principal | J8: 23.23 | K8: 0.15 | L8: =J8*(1+K8) -> 26.7145 | M8: =L8+F8 -> 26.7145 | N8: R0003
A9: 2026-07-23 14:30 PT | B9: Car rental scheduled pickup at Seattle-Tacoma International Airport. | C9: Principal | J9: =Expenses!G7 -> 307.77 | K9: 0.15 | L9: =J9*(1+K9) -> 353.9355 | M9: =L9+F9 -> 353.9355 | N9: R0005
A10: 2026-07-23 approx. 14:45 PT | B10: Left Seattle airport drive to Barkley Heights. | C10: Principal | D10: 3.75 | E10: 375 | F10: =E10*D10 -> 1406.25 | M10: =L10+F10 -> 1406.25
A11: 2026-07-23 approx. 18:05 PT | B11: Arrived at Barkley Heights job site; MetDavid Ebenal, inspected site, took observations, photographs etc | C11: Principal | D11: 1.5 | E11: 375 | F11: =E11*D11 -> 562.5 | M11: =L11+F11 -> 562.5
A12: 2026-07-23 19:30 PT | B12: Left Barkley Heights job site; Drive to hotel | C12: Principal | D12: 0.5 | E12: =E4 -> 187.5 | F12: =E12*D12 -> 93.75 | M12: =L12+F12 -> 93.75
A13: 2026-07-23 20:00 PT | B13: Check in Hotel | C13: Principal | J13: =Expenses!G5 -> 209.3 | K13: 0.15 | L13: =J13*(1+K13) -> 240.695 | M13: =L13+F13 -> 240.695 | N13: R0004
A14: 2026-07-23 20:00 PT | B14: Dinner Hotel | C14: Principal | J14: 25 | K14: 0.15 | L14: =J14*(1+K14) -> 28.75 | M14: =L14+F14 -> 28.75
A15: 2026-07-24 04:45 PT | B15: Left Bellingham hotel to drive back to Seattle airport. | C15: Principal | D15: 2.25 | E15: 375 | F15: =E15*D15 -> 843.75 | M15: =L15+F15 -> 843.75
A16: 2026-07-24 06:36 PT | B16: Purchased return-travel gasoline in SeaTac. | C16: Principal | J16: =Expenses!G8 -> 45.42 | K16: 0.15 | L16: =J16*(1+K16) -> 52.233 | M16: =L16+F16 -> 52.233 | N16: R0006
A17: 2026-07-24 07:40 PT | B17: Purchased return-travel breakfast at SEATAC Airport. | C17: Principal | J17: =Expenses!G9 -> 15.24 | K17: 0.15 | L17: =J17*(1+K17) -> 17.526 | M17: =L17+F17 -> 17.526 | N17: R0007
A18: 2026-07-24 07:30 PT | B18: Alaska 400 departed Seattle (SEA) for Santa Barbara (SBA). | C18: Principal
A19: 2026-07-24 13:30 PT | B19: Alaska 400 arrived Santa Barbara (SBA). | C19: Principal | D19: 6 | E19: =E4 -> 187.5 | F19: =E19*D19 -> 1125 | M19: =L19+F19 -> 1125
A20: 2026-07-24 14:00 PT | B20: Depart Santa Barbara Airport Parking | C20: Principal | J20: =Expenses!G10 -> 46 | K20: 0.15 | L20: =J20*(1+K20) -> 52.9 | M20: =L20+F20 -> 52.9 | N20: R0008
A21: 2026-07-23 14:30 PT | B21: Drive - Arrive Office | C21: Principal | D21: 0.5 | E21: =E4 -> 187.5 | F21: =E21*D21 -> 93.75 | G21: 30 | H21: miles | I21: 0.7 | J21: =I21*G21 -> 21 | K21: 0 | L21: =J21*(1+K21) -> 21 | M21: =L21+F21 -> 114.75
D22: =SUM(D4:D21) -> 20 | F22: =SUM(F4:F21) -> 5156.25 | L22: =SUM(L4:L21) -> 1867.602 | M22: =SUM(M4:M21) -> 7023.852
A23: Note: All travel time to and from Seattle charged at 50% of agreed rate

Sheet Invoice
C1: INVOICE | E1: Invoice No.: | F1: DSR1-2026-04-INV001
E2: Invoice Date: | F2: 2026-07-27
E4: Bill To:
A6: Matter | B6: Barkley Heights II, LLC v. Bradley Engineering - Whatcom County Case No. 26-2-01269-37
A7: Scope | B7: Site visit to subject wall prior to remediation work
A9: Professional Fees
A10: Date | B10: Description | E10: Hours | F10: Average Rate | G10: Total Fee
A11: 46226 | B11: Travel from Office to Site. Inspect subject wall | E11: =SUM(Itinerary!D4:D12) -> 11.25 | F11: =G11/E11 -> 275 | G11: =SUM(Itinerary!F4:F14) -> 3093.75
A12: 46227 | B12: Travel from Site to office | E12: =SUM(Itinerary!D14:D21) -> 8.75 | F12: =G12/E12 -> 235.71429 | G12: =SUM(Itinerary!F15:F21) -> 2062.5
A13: Total Fees | E13: =SUM(E11:E12) -> 20 | F13: =G13/E13 -> 257.8125 | G13: =SUM(G11:G12) -> 5156.25
A15: Reimbursable Expenses
A16: Date | B16: Description | D16: Receipt | E16: Actual Cost | F16: 15% Handling | G16: Amount
A17: 2026-07-22 | B17: Round-trip airfare for David Salter; confirmation INBEDI; e-ticket 0272152879104; Alaska 2143 SBA-SEA and Alaska 400 SEA-SBA | D17: R006 | E17: 896.8 | F17: =E17*0.15 -> 134.52 | G17: =E17+F17 -> 1031.32
A18: 2026-07-23 | B18: Breakfast - 16 oz dirty chai, butter croissant, tax, tip; check/order #221 | D18: R001 | E18: 18.72 | F18: =E18*0.15 -> 2.808 | G18: =E18+F18 -> 21.528
A19: 2026-07-23 | B19: Lunch ET FRUMAGE, Kit Kat bar, Barq's root beer, taxes; store 2366 transaction 116010 | D19: R002 | E19: 23.23 | F19: =E19*0.15 -> 3.4845 | G19: =E19+F19 -> 26.7145
A20: 2026-07-23 | B20: Car Rental - Mazda CX-50 or similar; confirmation 21886108US6; pickup 2026-07-23 14:30, drop-off 2026-07-24 14:30; estimated total shown on document | D20: R008 | E20: 307.77 | F20: =E20*0.15 -> 46.1655 | G20: =E20+F20 -> 353.9355
A21: 2026-07-23 | B21: Hotel - One night, Standard King Room, Booking.com confirmation 5674580542; total paid includes travel protection | D21: R007 | E21: 209.3 | F21: =E21*0.15 -> 31.395 | G21: =E21+F21 -> 240.695
A22: 2026-07-23 | B22: Dinnerl - Hotel restauraunt | D22: R004a | E22: 25 | F22: =E22*0.15 -> 3.75 | G22: =E22+F22 -> 28.75
A23: 2026-07-24 | B23: Gasoline, 7.327 gallons at $6.199/gallon; pump 2 invoice 063019 | D23: R003 | E23: 45.42 | F23: =E23*0.15 -> 6.813 | G23: =E23+F23 -> 52.233
A24: 2026-07-24 | B24: Breakfast - Large latte with vanilla and blueberry muffin; check 839 | D24: R004 | E24: 15.24 | F24: =E24*0.15 -> 2.286 | G24: =E24+F24 -> 17.526
A25: 2026-07-24 | B25: Airport parking; ticket 30472590; entry 2026-07-23 09:16 AM | D25: R005 | E25: 46 | F25: =E25*0.15 -> 6.9 | G25: =E25+F25 -> 52.9
A26: Total Reimbursable Expenses | E26: =SUM(E17:E25) -> 1587.48 | F26: =SUM(F17:F25) -> 238.122 | G26: =SUM(G17:G25) -> 1825.602
A28: Mileage
A29: Date | B29: Description | E29: Miles | F29: Rate / Mile | G29: Amount
A30: 2026-07-23 | B30: Office to Santa Barbara Airport | E30: 30 | F30: 0.7 | G30: =E30*F30 -> 21
A31: 2026-07-24 | B31: Office to Santa Barbara Airport | E31: 30 | F31: 0.7 | G31: =E31*F31 -> 21
A32: Total Mileage Expenses | E32: =SUM(E30:E31) -> 60 | F32: =G32/E32 -> 0.7 | G32: =SUM(G30:G31) -> 42
A34: Notes | B34: 1) Travel to and from Seattle charged at 50% of agreed hourly rate | E34: Professional Fees | G34: =G13 -> 5156.25
E35: Reimbursable Expenses | G35: =G26 -> 1825.602
E36: Mileage Expenses | G36: =G32 -> 42
F37: TOTAL DUE | G37: =SUM(G34:G36) -> 7023.852
